caioh_nvml_gpu_control/__init__.py
caioh_nvml_gpu_control/__main__.py
caioh_nvml_gpu_control/helper_functions.py
caioh_nvml_gpu_control/nvml_gpu_control.py
caioh_nvml_gpu_control/parse_args.py
caioh_nvml_gpu_control-2.1.4.1.dist-info/licenses/LICENSE
caioh_nvml_gpu_control-2.1.4.1.dist-info/METADATA
caioh_nvml_gpu_control-2.1.4.1.dist-info/WHEEL
caioh_nvml_gpu_control-2.1.4.1.dist-info/entry_points.txt
caioh_nvml_gpu_control-2.1.4.1.dist-info/top_level.txt
caioh_nvml_gpu_control-2.1.4.1.dist-info/RECORD
