Metadata-Version: 2.4
Name: caioh-nvml-gpu-control
Version: 2.1.4.1
Summary: A small program that uses the NVIDIA Management Library to control the GPU independent of OS or display server. This project is not provided or endorsed by NVIDIA
Author-email: Caio Gomes Flausino <caio.hacktestes@gmail.com>
Maintainer-email: Caio Gomes Flausino <caio.hacktestes@gmail.com>
License-Expression: GPL-2.0-or-later
Project-URL: Repository, https://github.com/HackTestes/NVML-GPU-Control
Keywords: NVIDIA,gpu,nvml,fan control,power control
Classifier: Development Status :: 5 - Production/Stable
Classifier: Environment :: Console
Classifier: Operating System :: Microsoft
Classifier: Operating System :: POSIX :: Linux
Classifier: Programming Language :: Python
Requires-Python: >=3.8
License-File: LICENSE
Requires-Dist: nvidia-ml-py>=13.580.65
Dynamic: license-file
